hatch_gitlab_publish/__about__.py
hatch_gitlab_publish/__init__.py
hatch_gitlab_publish-0.0.1.dev0.dist-info/METADATA
hatch_gitlab_publish-0.0.1.dev0.dist-info/WHEEL
hatch_gitlab_publish-0.0.1.dev0.dist-info/licenses/LICENSE.txt
hatch_gitlab_publish-0.0.1.dev0.dist-info/RECORD
