Metadata-Version: 2.1
Name: hatch-gitlab-publish
Version: 0.0.1.dev0
Summary: Hatch Publisher plugin to support publishing to a GitLab server package registry
Project-URL: Documentation, https://github.com/jamesdow21/hatch-gitlab-publish#readme
Project-URL: Issues, https://github.com/jamesdow21/hatch-gitlab-publish/issues
Project-URL: Source, https://github.com/jamesdow21/hatch-gitlab-publish
Author-email: James Dow <jamesdow21@gmail.com>
License-Expression: MIT
License-File: LICENSE.txt
Classifier: Development Status :: 4 - Beta
Classifier: Programming Language :: Python
Classifier: Programming Language :: Python :: 3.7
Classifier: Programming Language :: Python :: 3.8
Classifier: Programming Language :: Python :: 3.9
Classifier: Programming Language :: Python :: 3.10
Classifier: Programming Language :: Python :: 3.11
Classifier: Programming Language :: Python :: Implementation :: CPython
Requires-Python: >=3.7
Requires-Dist: hatch
